{
  "version": 1,
  "feature": "say_hello",
  "kind": "http",
  "relevant_files": [
    "app/features/say_hello/feature.yaml",
    "app/features/say_hello/action.php",
    "app/features/say_hello/input.schema.json",
    "app/features/say_hello/output.schema.json",
    "app/features/say_hello/permissions.yaml",
    "app/features/say_hello/events.yaml",
    "app/features/say_hello/jobs.yaml",
    "app/features/say_hello/cache.yaml",
    "app/features/say_hello/prompts.md",
    "app/features/say_hello/tests/say_hello_contract_test.php",
    "app/features/say_hello/tests/say_hello_feature_test.php"
  ],
  "generated_files": [
    "app/generated/routes.php",
    "app/generated/feature_index.php",
    "app/generated/schema_index.php"
  ],
  "upstream_dependencies": [],
  "downstream_dependents": [],
  "contracts": {
    "input": "app/features/say_hello/input.schema.json",
    "output": "app/features/say_hello/output.schema.json"
  },
  "tests": [
    "say_hello_contract_test",
    "say_hello_feature_test"
  ],
  "forbidden_paths": [
    "src/Core",
    "src/Http"
  ],
  "risk_level": "low"
}
